admetscore/__init__.py
admetscore/app.py
admetscore/models/BrowserHandler.py
admetscore/models/Evaluate.py
admetscore/models/Merge.py
admetscore/models/Output.py
admetscore/models/Screening.py
admetscore/models/Splitter.py
admetscore/models/texts.py
admetscore/weights.json
admetscore-1.0.1.dist-info/METADATA
admetscore-1.0.1.dist-info/WHEEL
admetscore-1.0.1.dist-info/entry_points.txt
admetscore-1.0.1.dist-info/RECORD
