Metadata-Version: 2.1
Name: admetscore
Version: 1.0.1
Summary: The ADMETSCORE is a software that aims to facilitate the ADMET analysis of molecules resulting from pharmacophore research.
Author: Julio Cesar Xavier
Author-email: jcaxavier2@gmail.com
Requires-Python: >=3.10,<4.0
Classifier: Programming Language :: Python :: 3
Classifier: Programming Language :: Python :: 3.10
Classifier: Programming Language :: Python :: 3.11
Classifier: Programming Language :: Python :: 3.12
Requires-Dist: XlsxWriter (>=3.2.0,<4.0.0)
Requires-Dist: numpy (==1.26.4)
Requires-Dist: openpyxl (>=3.1.5,<4.0.0)
Requires-Dist: pandas (>=2.2.2,<3.0.0)
Requires-Dist: rdkit (>=2023.9.3,<2024.0.0)
Requires-Dist: selenium (>=4.23.1,<5.0.0)
Requires-Dist: webdriver-manager (>=4.0.2,<5.0.0)
